cogniz/__init__.py
cogniz/client.py
cogniz/config.py
cogniz/errors.py
cogniz/py.typed
cogniz-1.0.1.dist-info/licenses/LICENSE
cogniz-1.0.1.dist-info/METADATA
cogniz-1.0.1.dist-info/WHEEL
cogniz-1.0.1.dist-info/top_level.txt
cogniz-1.0.1.dist-info/RECORD
