Metadata-Version: 2.4
Name: cogniz
Version: 1.0.1
Summary: Python SDK for Cogniz Memory Platform - Persistent memory for AI applications
Author-email: Cogniz Team <support@cogniz.online>
License: MIT
Project-URL: Homepage, https://cogniz.online
Project-URL: Documentation, https://docs.cogniz.online
Project-URL: Repository, https://github.com/cogniz-ai/cogniz-python
Project-URL: Changelog, https://github.com/cogniz-ai/cogniz-python/blob/main/CHANGELOG.md
Project-URL: Issues, https://github.com/cogniz-ai/cogniz-python/issues
Keywords: ai,memory,llm,rag,agent,chatbot,embeddings,langchain,llama index
Classifier: Development Status :: 5 - Production/Stable
Classifier: Intended Audience :: Developers
Classifier: License :: OSI Approved :: MIT License
Classifier: Programming Language :: Python :: 3
Classifier: Programming Language :: Python :: 3.8
Classifier: Programming Language :: Python :: 3.9
Classifier: Programming Language :: Python :: 3.10
Classifier: Programming Language :: Python :: 3.11
Classifier: Programming Language :: Python :: 3.12
Classifier: Topic :: Software Development :: Libraries :: Python Modules
Classifier: Topic :: Scientific/Engineering :: Artificial Intelligence
Requires-Python: >=3.8
License-File: LICENSE
Requires-Dist: httpx>=0.24.0
Provides-Extra: dev
Requires-Dist: pytest>=7.4.0; extra == "dev"
Requires-Dist: pytest-asyncio>=0.21.0; extra == "dev"
Requires-Dist: pytest-cov>=4.1.0; extra == "dev"
Requires-Dist: pytest-httpx>=0.22.0; extra == "dev"
Requires-Dist: black>=23.7.0; extra == "dev"
Requires-Dist: mypy>=1.5.0; extra == "dev"
Requires-Dist: ruff>=0.1.0; extra == "dev"
Dynamic: license-file
